{
  "xsappname": "risk-management",
  "tenant-mode": "dedicated",
  "description": "Security profile of called application",
  "scopes": [
    {
      "name": "$XSAPPNAME.RiskViewer",
      "description": "RiskViewer"
    },
    {
      "name": "$XSAPPNAME.RiskManager",
      "description": "RiskManager"
    }
  ],
  "role-templates": [
    {
      "name": "RiskViewer",
      "description": "generated",
      "scope-references": [
        "$XSAPPNAME.RiskViewer"
      ],
      "attribute-references": []
    },
    {
      "name": "RiskManager",
      "description": "generated",
      "scope-references": [
        "$XSAPPNAME.RiskManager"
      ],
      "attribute-references": []
    }
  ],
  "attributes": [],
  "oauth2-configuration": {
    "redirect-uris": [
      "https://f17611e0trial-dev-risk-management.cfapps.us10-001.hana.ondemand.com/login/callback",
      "https://port5000-workspaces-ws-545cx.us10.trial.applicationstudio.cloud.sap/login/callback",
      "https://**.hana.ondemand.com/login/callback",
      "https://**.applicationstudio.cloud.sap/login/callback",
      "https://************-risk-management.cfapps.us10-001.hana.ondemand.com",
      "https://*.cfapps.us10-001.hana.ondemand.com/**",
      "*",
      "https://f17611e0trial.authentication.us10.hana.ondemand.com/oauth/*",
      "https://*.hana.ondemand.com/**"
    ]
  }
}
